<?xml version="1.0" encoding="UTF-8"?>
<objects serializationModel="Studio.02.01.00">
	<object class="AudioFile" id="{a5f605f5-956d-4b41-85b4-5e938687309a}">
		<property name="assetPath">
			<value>tutorial music.wav</value>
		</property>
		<property name="isStreaming">
			<value>true</value>
		</property>
		<property name="frequencyInKHz">
			<value>44.0999985</value>
		</property>
		<property name="channelCount">
			<value>2</value>
		</property>
		<property name="length">
			<value>73.846145124716557</value>
		</property>
		<relationship name="masterAssetFolder">
			<destination>{effef780-ca89-455f-ae27-d03fbd6a7364}</destination>
		</relationship>
	</object>
</objects>
